pyuu/shell/__init__.py
pyuu.shell-0.0.2.dist-info/METADATA
pyuu.shell-0.0.2.dist-info/WHEEL
pyuu.shell-0.0.2.dist-info/top_level.txt
pyuu.shell-0.0.2.dist-info/RECORD
