Metadata-Version: 2.1
Name: pyuu.shell
Version: 0.0.2
Summary: shell utils
Home-page: https://github.com/happyxianyu/uu
Author: happyxianyu
Author-email: happyxianyu623@outlook.com
License: Apache License 2.0
Requires-Python: >=3.8
